jaccard/__init__.py
jaccard/jaccard.py
boolean_jaccard-0.1.1.dist-info/LICENSE
boolean_jaccard-0.1.1.dist-info/WHEEL
boolean_jaccard-0.1.1.dist-info/METADATA
boolean_jaccard-0.1.1.dist-info/RECORD
