Metadata-Version: 2.1
Name: boolean-jaccard
Version: 0.1.1
Summary: Jaccard metric calculations for boolean vectors
Home-page: https://github.com/IMS-Bio2Core-Facility/boolean_jaccard
License: MIT
Author: rbpatt2019
Author-email: rb.patterson.cross@gmail.com
Requires-Python: >=3.8.0,<3.11
Classifier: Development Status :: 5 - Production/Stable
Classifier: Environment :: Console
Classifier: Intended Audience :: Science/Research
Classifier: License :: OSI Approved :: MIT License
Classifier: Operating System :: OS Independent
Classifier: Programming Language :: Python
Classifier: Programming Language :: Python :: 3
Classifier: Programming Language :: Python :: 3.10
Classifier: Programming Language :: Python :: 3.8
Classifier: Programming Language :: Python :: 3.9
Classifier: Topic :: Scientific/Engineering
Classifier: Topic :: Scientific/Engineering :: Bio-Informatics
Classifier: Typing :: Typed
Requires-Dist: numpy (>=1.22.3,<2.0.0)
Requires-Dist: pandas (>=1.4.2,<2.0.0)
Project-URL: Documentation, https://boolean_jaccard.readthedocs.io/en/latest/
Project-URL: Repository, https://github.com/IMS-Bio2Core-Facility/boolean_jaccard
